{"repositories":[{"has_downloads":true,"url":"https://github.com/svenfuchs/safemode","watchers":34,"description":"A library for safe evaluation of Ruby code based on ParseTree/RubyParser and Ruby2Ruby. Provides Rails ActionView template handlers for ERB and Haml.","fork":false,"has_wiki":true,"open_issues":0,"homepage":"http://www.artweb-design.de","size":592,"private":false,"name":"safemode","forks":5,"owner":"svenfuchs","has_issues":true,"language":"Ruby","created_at":"2008/04/29 06:36:07 -0700","pushed_at":"2010/03/29 06:57:19 -0700"},{"has_downloads":true,"url":"https://github.com/svenfuchs/scriptaculous-sortabletree","watchers":35,"description":"Implements a sortable tree for scriptacolous","fork":false,"has_wiki":true,"open_issues":0,"homepage":"http://www.artweb-design.de","size":156,"private":false,"name":"scriptaculous-sortabletree","forks":4,"owner":"svenfuchs","has_issues":true,"language":"JavaScript","created_at":"2008/05/11 04:25:28 -0700","pushed_at":"2008/10/11 14:45:38 -0700"},{"has_downloads":true,"url":"https://github.com/svenfuchs/stubby","watchers":3,"description":"lightweight and fast stubbing framework","fork":false,"has_wiki":true,"open_issues":0,"homepage":"http://www.artweb-design.de","size":128,"private":false,"name":"stubby","forks":0,"owner":"svenfuchs","has_issues":true,"created_at":"2008/05/29 11:20:08 -0700","pushed_at":"2008/05/30 09:37:35 -0700"},{"has_downloads":true,"url":"https://github.com/svenfuchs/routing-filter","watchers":213,"description":"routing-filter wraps around the complex beast that the Rails routing system is, allowing for unseen flexibility and power in Rails URL recognition and generation.","fork":false,"has_wiki":true,"open_issues":9,"homepage":"http://www.artweb-design.de","size":208,"private":false,"name":"routing-filter","forks":39,"owner":"svenfuchs","has_issues":true,"language":"Ruby","created_at":"2008/05/29 16:08:07 -0700","pushed_at":"2011/07/13 06:20:08 -0700"},{"has_downloads":true,"url":"https://github.com/svenfuchs/reference_tracking","watchers":13,"description":"","fork":false,"has_wiki":true,"open_issues":0,"homepage":"http://www.artweb-design.de","size":1264,"private":false,"name":"reference_tracking","forks":1,"owner":"svenfuchs","has_issues":true,"language":"Ruby","created_at":"2008/05/30 09:57:08 -0700","pushed_at":"2010/11/29 00:46:42 -0800"},{"has_downloads":true,"url":"https://github.com/svenfuchs/adva_cms","watchers":476,"description":"cutting edge cms, blog, wiki, forum ...","fork":false,"has_wiki":true,"open_issues":9,"homepage":"http://adva-cms.org","size":1792,"private":false,"name":"adva_cms","forks":55,"owner":"svenfuchs","has_issues":true,"language":"JavaScript","created_at":"2008/06/04 13:18:09 -0700","pushed_at":"2011/07/30 03:01:55 -0700"},{"has_downloads":true,"url":"https://github.com/svenfuchs/i18n","watchers":297,"description":"Internationalization (i18n) library for Ruby","fork":true,"has_wiki":true,"open_issues":18,"homepage":"rails-i18n.org/wiki","size":372,"private":false,"name":"i18n","forks":63,"owner":"svenfuchs","has_issues":true,"language":"Ruby","integrate_branch":"master","created_at":"2008/06/13 05:47:13 -0700","pushed_at":"2011/07/10 09:00:28 -0700"},{"has_downloads":true,"url":"https://github.com/svenfuchs/rails","watchers":5,"description":"Ruby on Rails - forked for implementing I18n patch","fork":true,"has_wiki":true,"open_issues":0,"homepage":"http://rubyonrails.org","size":140,"private":false,"name":"rails","forks":2,"owner":"svenfuchs","has_issues":true,"language":"Ruby","created_at":"2008/06/18 07:49:29 -0700","pushed_at":"2011/07/14 12:18:59 -0700"},{"has_downloads":true,"url":"https://github.com/svenfuchs/rails-i18n","watchers":1028,"description":"Repository for collecting Locale data for Ruby on Rails I18n as well as other interesting, Rails related I18n stuff","fork":false,"has_wiki":true,"open_issues":2,"homepage":"http://rails-i18n.org","size":988,"private":false,"name":"rails-i18n","forks":216,"owner":"svenfuchs","has_issues":true,"language":"Ruby","created_at":"2008/07/31 06:07:53 -0700","pushed_at":"2011/08/03 05:00:42 -0700"},{"has_downloads":true,"url":"https://github.com/svenfuchs/scrumtious","watchers":5,"description":"toying with a remote scrum tool pulling from lighthouse for","fork":false,"has_wiki":true,"open_issues":0,"homepage":"","size":6144,"private":false,"name":"scrumtious","forks":0,"owner":"svenfuchs","has_issues":true,"language":"Ruby","created_at":"2008/10/04 10:36:15 -0700","pushed_at":"2008/11/03 03:42:48 -0800"},{"has_downloads":true,"url":"https://github.com/svenfuchs/test_server","watchers":5,"description":"Playing around with a test server for Rails that keeps the environment loaded (just like spec_server)","fork":false,"has_wiki":true,"open_issues":0,"homepage":"","size":568,"private":false,"name":"test_server","forks":0,"owner":"svenfuchs","has_issues":true,"created_at":"2008/11/22 14:07:42 -0800","pushed_at":"2009/01/25 15:22:27 -0800"},{"has_downloads":true,"url":"https://github.com/svenfuchs/with","watchers":6,"description":"highly experimental, lightweight and flexible contexts for test/unit","fork":false,"has_wiki":true,"open_issues":0,"homepage":"","size":1024,"private":false,"name":"with","forks":0,"owner":"svenfuchs","has_issues":true,"language":"Ruby","created_at":"2008/12/01 02:38:35 -0800","pushed_at":"2009/01/25 15:20:47 -0800"},{"has_downloads":true,"url":"https://github.com/svenfuchs/with-sugar","watchers":2,"description":"Test macros for being used with With","fork":false,"has_wiki":true,"open_issues":0,"homepage":"","size":232,"private":false,"name":"with-sugar","forks":1,"owner":"svenfuchs","has_issues":true,"language":"Ruby","created_at":"2008/12/30 03:43:05 -0800","pushed_at":"2009/01/25 15:21:34 -0800"},{"has_downloads":true,"url":"https://github.com/svenfuchs/mephisto_full_archives","watchers":1,"description":"simple plugin that adds a full archives view to Mephisto's own archives","fork":false,"has_wiki":true,"open_issues":0,"homepage":"http://www.artweb-design.de/projects/mephisto-plugin-full-archives","size":156,"private":false,"name":"mephisto_full_archives","forks":0,"owner":"svenfuchs","has_issues":true,"created_at":"2009/03/30 14:03:52 -0700","pushed_at":"2009/03/30 15:09:07 -0700"},{"has_downloads":true,"url":"https://github.com/svenfuchs/mephisto_inverse_captcha","watchers":1,"description":"Mephisto anti-comment-spam plugin that adds an \"outer floodgate\" to the existing (Akismet) spam-protection","fork":false,"has_wiki":true,"open_issues":0,"homepage":"http://www.artweb-design.de/projects/mephisto-plugin-inverse-captcha-for-comments-anti-spam","size":216,"private":false,"name":"mephisto_inverse_captcha","forks":0,"owner":"svenfuchs","has_issues":true,"created_at":"2009/03/30 14:12:26 -0700","pushed_at":"2009/03/30 15:27:10 -0700"},{"has_downloads":true,"url":"https://github.com/svenfuchs/mephisto_paged_article_list","watchers":6,"description":"Mephisto doesn't page article lists out of the box. This plugin adds that.","fork":false,"has_wiki":true,"open_issues":0,"homepage":"http://www.artweb-design.de/projects/mephisto-plugin-paged-article-lists","size":220,"private":false,"name":"mephisto_paged_article_list","forks":0,"owner":"svenfuchs","has_issues":true,"created_at":"2009/03/30 14:16:39 -0700","pushed_at":"2009/03/30 15:28:25 -0700"},{"has_downloads":true,"url":"https://github.com/svenfuchs/mephisto_tag_cloud","watchers":2,"description":"Most complete, sophisticated, standard-conform and allover-awesome implementation of a tag cloud plugin for Mephisto :)","fork":false,"has_wiki":true,"open_issues":0,"homepage":"http://www.artweb-design.de/projects/mephisto-plugin-tag-cloud","size":252,"private":false,"name":"mephisto_tag_cloud","forks":1,"owner":"svenfuchs","has_issues":true,"created_at":"2009/03/30 14:19:23 -0700","pushed_at":"2010/08/11 05:05:52 -0700"},{"has_downloads":true,"url":"https://github.com/svenfuchs/google_analytics","watchers":3,"description":"This plugin is primarily targeted at being used with Mephisto but should be useful with other Rails based CMS or blogging plattforms, too.","fork":false,"has_wiki":true,"open_issues":0,"homepage":"http://www.artweb-design.de/projects/ruby-on-rails-plugin-google-analytics","size":196,"private":false,"name":"google_analytics","forks":0,"owner":"svenfuchs","has_issues":true,"language":"Ruby","created_at":"2009/03/30 14:24:44 -0700","pushed_at":"2009/03/30 15:22:56 -0700"},{"has_downloads":true,"url":"https://github.com/svenfuchs/will_paginate_liquidized","watchers":2,"description":"This plugin allows you to use will_paginate with Liquid templates. That's it.","fork":false,"has_wiki":true,"open_issues":0,"homepage":"http://www.artweb-design.de/projects/ruby-on-rails-plugin-will_paginate-liquidized","size":156,"private":false,"name":"will_paginate_liquidized","forks":0,"owner":"svenfuchs","has_issues":true,"created_at":"2009/03/30 14:40:02 -0700","pushed_at":"2009/03/30 15:23:16 -0700"},{"has_downloads":true,"url":"https://github.com/svenfuchs/taskmate","watchers":3,"description":"Simplistic TextMate bundle for getting more done with your favorite missing text editor.","fork":false,"has_wiki":true,"open_issues":0,"homepage":"http://www.artweb-design.de/projects/taskmate","size":384,"private":false,"name":"taskmate","forks":2,"owner":"svenfuchs","has_issues":true,"language":"Ruby","created_at":"2009/03/30 14:50:34 -0700","pushed_at":"2009/03/30 14:51:03 -0700"},{"has_downloads":true,"url":"https://github.com/svenfuchs/i18n-tools","watchers":10,"description":"Tools for working with ruby/rails i18n","fork":false,"has_wiki":true,"open_issues":0,"homepage":"http://rails-i18n.org","size":3072,"private":false,"name":"i18n-tools","forks":2,"owner":"svenfuchs","has_issues":true,"created_at":"2009/05/26 02:52:04 -0700","pushed_at":"2009/07/05 04:23:04 -0700"},{"has_downloads":true,"url":"https://github.com/svenfuchs/ripper2ruby","watchers":33,"description":"Similar to ruby2ruby this library allows to parse Ruby code, modify and recompile it back to Ruby.","fork":false,"has_wiki":true,"open_issues":2,"homepage":"http://www.artweb-design.de","size":2048,"private":false,"name":"ripper2ruby","forks":9,"owner":"svenfuchs","has_issues":true,"language":"Ruby","integrate_branch":"master","created_at":"2009/06/13 09:42:32 -0700","pushed_at":"2009/08/22 02:58:45 -0700"},{"has_downloads":true,"url":"https://github.com/svenfuchs/rbac","watchers":3,"description":"","fork":false,"has_wiki":true,"open_issues":0,"homepage":"","size":1740,"private":false,"name":"rbac","forks":1,"owner":"svenfuchs","has_issues":true,"created_at":"2009/07/14 05:59:51 -0700","pushed_at":"2009/10/27 06:25:25 -0700"},{"has_downloads":true,"url":"https://github.com/svenfuchs/progit","watchers":19,"description":"Pro Git Book Content - German Translation -> /de/README","fork":true,"has_wiki":true,"open_issues":0,"homepage":"http://progit.org","size":156,"private":false,"name":"progit","forks":3,"owner":"svenfuchs","has_issues":false,"language":"JavaScript","created_at":"2009/07/30 05:44:39 -0700","pushed_at":"2011/07/23 07:26:49 -0700"},{"has_downloads":true,"url":"https://github.com/svenfuchs/rack-cache","watchers":1,"description":"Real HTTP Caching for Ruby Web Apps","fork":true,"has_wiki":true,"open_issues":0,"homepage":"http://tomayko.com/src/rack-cache/","size":580,"private":false,"name":"rack-cache","forks":1,"owner":"svenfuchs","has_issues":false,"created_at":"2009/08/30 10:54:11 -0700","pushed_at":"2009/09/09 06:59:38 -0700"},{"has_downloads":true,"url":"https://github.com/svenfuchs/rack-cache-purge","watchers":11,"description":"Support for purging rack-cache","fork":false,"has_wiki":true,"open_issues":0,"homepage":"","size":1148,"private":false,"name":"rack-cache-purge","forks":3,"owner":"svenfuchs","has_issues":true,"language":"Ruby","created_at":"2009/09/02 03:24:36 -0700","pushed_at":"2010/12/05 05:12:19 -0800"},{"has_downloads":true,"url":"https://github.com/svenfuchs/rack-cache-tags","watchers":3,"description":"Support for tagging rack-cache entries","fork":false,"has_wiki":true,"open_issues":0,"homepage":"","size":1368,"private":false,"name":"rack-cache-tags","forks":1,"owner":"svenfuchs","has_issues":true,"created_at":"2009/09/09 11:25:20 -0700","pushed_at":"2010/10/15 11:53:13 -0700"},{"has_downloads":true,"url":"https://github.com/svenfuchs/steam","watchers":58,"description":"Headless integration testing w/ HtmlUnit: enables testing JavaScript-driven web sites","fork":false,"has_wiki":true,"open_issues":3,"homepage":"","size":336,"private":false,"master_branch":"master","name":"steam","forks":4,"owner":"svenfuchs","has_issues":true,"language":"JavaScript","created_at":"2009/10/04 10:19:18 -0700","pushed_at":"2010/12/16 16:38:11 -0800"},{"has_downloads":true,"url":"https://github.com/svenfuchs/vim-tree","watchers":11,"description":"vim filesystem tree plugin in ruby","fork":false,"has_wiki":true,"open_issues":3,"homepage":"","size":3228,"private":false,"name":"vim-tree","forks":3,"owner":"svenfuchs","has_issues":true,"language":"Ruby","created_at":"2009/10/29 04:19:37 -0700","pushed_at":"2010/10/17 11:00:30 -0700"},{"has_downloads":true,"url":"https://github.com/svenfuchs/ruby-cldr","watchers":8,"description":"Ruby library for exporting data from CLDR (Common Locale Data Repository)","fork":false,"has_wiki":true,"open_issues":1,"homepage":"","size":8704,"private":false,"master_branch":"master","name":"ruby-cldr","forks":2,"owner":"svenfuchs","has_issues":true,"language":"Ruby","created_at":"2009/11/21 07:45:44 -0800","pushed_at":"2010/01/20 04:08:12 -0800"},{"has_downloads":true,"url":"https://github.com/svenfuchs/activemodel-error","watchers":8,"description":"I18n support for validation error messages in ActiveModel","fork":false,"has_wiki":true,"open_issues":1,"homepage":"","size":3200,"private":false,"name":"activemodel-error","forks":1,"owner":"svenfuchs","has_issues":true,"created_at":"2010/01/23 18:08:29 -0800","pushed_at":"2010/02/25 08:14:06 -0800"},{"has_downloads":true,"url":"https://github.com/svenfuchs/locator","watchers":9,"description":"Generic html element locators for testing tools","fork":false,"has_wiki":true,"open_issues":1,"homepage":"http://github.com/svenfuchs/locator","size":3472,"private":false,"name":"locator","forks":1,"owner":"svenfuchs","has_issues":true,"language":"Ruby","created_at":"2010/02/03 06:52:07 -0800","pushed_at":"2010/12/16 16:40:14 -0800"},{"has_downloads":true,"url":"https://github.com/svenfuchs/i18n-message","watchers":4,"description":"Object-oriented abstraction for looking up translations from I18n.translate","fork":false,"has_wiki":true,"open_issues":0,"homepage":"http://github.com/svenfuchs/i18n_message","size":596,"private":false,"name":"i18n-message","forks":1,"owner":"svenfuchs","has_issues":true,"language":"Ruby","created_at":"2010/02/25 04:16:33 -0800","pushed_at":"2010/10/31 10:11:39 -0700"},{"has_downloads":true,"url":"https://github.com/svenfuchs/minimal","watchers":22,"description":"Minimal templating engine inspired by Markaby & Erector but much smaller and targeting Rails 3","fork":false,"has_wiki":true,"open_issues":0,"homepage":"http://github.com/svenfuchs/minimal","size":456,"private":false,"name":"minimal","forks":4,"owner":"svenfuchs","has_issues":true,"language":"Ruby","created_at":"2010/03/06 04:52:35 -0800","pushed_at":"2011/05/09 03:54:03 -0700"},{"has_downloads":true,"url":"https://github.com/svenfuchs/svenfuchs.github.com","watchers":1,"description":"jo","fork":false,"has_wiki":true,"open_issues":0,"homepage":"svenfuchs.github.com","size":9612,"private":false,"name":"svenfuchs.github.com","forks":1,"owner":"svenfuchs","has_issues":true,"language":"JavaScript","created_at":"2010/03/14 12:21:30 -0700","pushed_at":"2011/07/26 15:55:29 -0700"},{"has_downloads":true,"url":"https://github.com/svenfuchs/statics","watchers":1,"description":"","fork":false,"has_wiki":true,"open_issues":0,"homepage":"","size":116,"private":false,"name":"statics","forks":1,"owner":"svenfuchs","has_issues":true,"created_at":"2010/03/20 16:57:37 -0700","pushed_at":"2010/03/20 17:27:39 -0700"},{"has_downloads":true,"url":"https://github.com/svenfuchs/identity","watchers":1,"description":"","fork":false,"has_wiki":true,"open_issues":0,"homepage":"","size":1972,"private":false,"name":"identity","forks":1,"owner":"svenfuchs","has_issues":true,"created_at":"2010/03/21 11:48:43 -0700","pushed_at":"2010/04/01 09:23:46 -0700"},{"has_downloads":true,"url":"https://github.com/svenfuchs/command","watchers":1,"description":"","fork":false,"has_wiki":true,"open_issues":0,"homepage":"","size":252,"private":false,"name":"command","forks":1,"owner":"svenfuchs","has_issues":true,"created_at":"2010/03/28 10:19:34 -0700","pushed_at":"2010/04/01 09:25:06 -0700"},{"has_downloads":true,"url":"https://github.com/svenfuchs/gem-release","watchers":44,"description":"Release your ruby gems with ease. (What a bold statement for such a tiny plugin ...)","fork":false,"has_wiki":true,"open_issues":3,"homepage":"","size":180,"private":false,"name":"gem-release","forks":6,"owner":"svenfuchs","has_issues":true,"language":"Ruby","created_at":"2010/04/02 17:04:17 -0700","pushed_at":"2011/07/29 06:43:14 -0700"},{"has_downloads":true,"url":"https://github.com/svenfuchs/test_declarative","watchers":2,"description":"Simply adds a declarative test method syntax to test/unit","fork":false,"has_wiki":true,"open_issues":0,"homepage":"","size":152,"private":false,"name":"test_declarative","forks":2,"owner":"svenfuchs","has_issues":true,"created_at":"2010/04/04 05:24:46 -0700","pushed_at":"2010/12/26 11:57:22 -0800"},{"has_downloads":true,"url":"https://github.com/svenfuchs/uki_reader","watchers":3,"description":"Experimental Google Reader UI based on Uki","fork":false,"has_wiki":true,"open_issues":0,"homepage":"","size":392,"private":false,"name":"uki_reader","forks":1,"owner":"svenfuchs","has_issues":true,"created_at":"2010/04/11 05:38:56 -0700","pushed_at":"2010/04/11 06:04:11 -0700"},{"has_downloads":true,"url":"https://github.com/svenfuchs/adva-cms2","watchers":115,"description":"Cutting edge Rails 3 CMS framework","fork":false,"has_wiki":true,"open_issues":2,"homepage":"adva-cms.org","size":148,"private":false,"master_branch":"develop","name":"adva-cms2","forks":9,"owner":"svenfuchs","has_issues":true,"language":"Ruby","created_at":"2010/04/12 08:16:45 -0700","pushed_at":"2011/07/29 07:58:59 -0700"},{"has_downloads":true,"url":"https://github.com/svenfuchs/rjb-require","watchers":1,"description":"Adds the ability to import and map Java packages to nested Ruby modules/classes to RJB.","fork":false,"has_wiki":true,"open_issues":0,"homepage":"","size":132,"private":false,"name":"rjb-require","forks":1,"owner":"svenfuchs","has_issues":true,"created_at":"2010/04/30 08:59:06 -0700","pushed_at":"2010/04/30 09:00:36 -0700"},{"has_downloads":true,"url":"https://github.com/svenfuchs/taka","watchers":4,"description":"Taka is a DOM (core and html) implementation for Ruby","fork":true,"has_wiki":true,"open_issues":0,"homepage":"","size":3668,"private":false,"name":"taka","forks":2,"owner":"svenfuchs","has_issues":false,"created_at":"2010/05/01 03:27:43 -0700","pushed_at":"2010/05/09 15:38:10 -0700"},{"has_downloads":true,"url":"https://github.com/svenfuchs/dom-test-suite","watchers":1,"description":"2001 Dom test suite","fork":true,"has_wiki":true,"open_issues":0,"homepage":"","size":6144,"private":false,"name":"dom-test-suite","forks":1,"owner":"svenfuchs","has_issues":false,"created_at":"2010/05/02 05:03:49 -0700","pushed_at":"2008/08/31 16:22:21 -0700"},{"has_downloads":true,"url":"https://github.com/svenfuchs/dom-test","watchers":1,"description":"Ruby export of Level 1 and 2 W3C DOM tests","fork":false,"has_wiki":true,"open_issues":0,"homepage":"","size":2576,"private":false,"name":"dom-test","forks":1,"owner":"svenfuchs","has_issues":true,"created_at":"2010/05/16 06:42:43 -0700","pushed_at":"2010/05/16 06:45:27 -0700"},{"has_downloads":true,"url":"https://github.com/svenfuchs/rdom","watchers":21,"description":"experimental browser implementation in ruby using nokogiri and johnson","fork":false,"has_wiki":true,"open_issues":1,"homepage":"","size":1188,"private":false,"name":"rdom","forks":5,"owner":"svenfuchs","has_issues":true,"language":"Ruby","integrate_branch":"v8","created_at":"2010/05/16 06:46:14 -0700","pushed_at":"2010/08/11 05:11:21 -0700"},{"has_downloads":true,"url":"https://github.com/svenfuchs/treetop_css","watchers":2,"description":"Treetop CSS grammar/parser","fork":false,"has_wiki":true,"open_issues":0,"homepage":"","size":720,"private":false,"name":"treetop_css","forks":1,"owner":"svenfuchs","has_issues":true,"language":"Ruby","created_at":"2010/05/19 16:16:15 -0700","pushed_at":"2010/05/23 05:14:30 -0700"},{"has_downloads":true,"url":"https://github.com/svenfuchs/capture_stdout","watchers":2,"description":"Adds Kernel.capture_stdout(&block). Useful e.g. for testing command line tools","fork":false,"has_wiki":true,"open_issues":0,"homepage":"http://github.com/svenfuchs/capture_stdout","size":128,"private":false,"name":"capture_stdout","forks":1,"owner":"svenfuchs","has_issues":true,"created_at":"2010/06/10 07:48:59 -0700","pushed_at":"2010/06/10 08:14:08 -0700"},{"has_downloads":true,"url":"https://github.com/svenfuchs/silence_log_tailer","watchers":1,"description":"Silence rails/server log tailing to console","fork":false,"has_wiki":true,"open_issues":0,"homepage":"","size":136,"private":false,"name":"silence_log_tailer","forks":1,"owner":"svenfuchs","has_issues":true,"created_at":"2010/07/07 02:56:47 -0700","pushed_at":"2010/07/07 02:57:24 -0700"},{"has_downloads":true,"url":"https://github.com/svenfuchs/simple_nested_set","watchers":26,"fork":false,"has_wiki":true,"open_issues":0,"size":1820,"private":false,"name":"simple_nested_set","forks":5,"owner":"svenfuchs","has_issues":true,"language":"Ruby","created_at":"2010/07/17 07:57:53 -0700","pushed_at":"2011/08/07 06:31:12 -0700"},{"has_downloads":true,"url":"https://github.com/svenfuchs/pathname_local","watchers":1,"fork":false,"has_wiki":true,"open_issues":0,"size":156,"private":false,"name":"pathname_local","forks":1,"owner":"svenfuchs","has_issues":true,"created_at":"2010/07/17 08:17:14 -0700","pushed_at":"2010/07/17 08:27:35 -0700"},{"has_downloads":true,"url":"https://github.com/svenfuchs/simple_taggable","watchers":3,"fork":false,"has_wiki":true,"open_issues":0,"size":740,"private":false,"name":"simple_taggable","forks":1,"owner":"svenfuchs","has_issues":true,"created_at":"2010/07/18 03:59:14 -0700","pushed_at":"2010/10/16 07:11:50 -0700"},{"has_downloads":true,"url":"https://github.com/svenfuchs/globalize3","watchers":178,"description":"","fork":false,"has_wiki":true,"open_issues":8,"homepage":"","size":416,"private":false,"name":"globalize3","forks":36,"owner":"svenfuchs","has_issues":true,"language":"Ruby","created_at":"2010/07/30 07:30:27 -0700","pushed_at":"2011/08/04 06:06:41 -0700"},{"has_downloads":true,"url":"https://github.com/svenfuchs/simple_slugs","watchers":6,"description":"","fork":false,"has_wiki":true,"open_issues":0,"homepage":"","size":1232,"private":false,"name":"simple_slugs","forks":1,"owner":"svenfuchs","has_issues":true,"created_at":"2010/07/31 09:51:38 -0700","pushed_at":"2010/11/20 14:25:21 -0800"},{"has_downloads":true,"url":"https://github.com/svenfuchs/ruby-i18n.org","watchers":1,"description":"ruby-i18n.org - static html export, see the source branch for sources","fork":false,"has_wiki":true,"open_issues":0,"homepage":"ruby-i18n.org","size":192,"private":false,"name":"ruby-i18n.org","forks":1,"owner":"svenfuchs","has_issues":true,"created_at":"2010/08/21 14:14:59 -0700","pushed_at":"2010/08/22 07:47:57 -0700"},{"has_downloads":true,"url":"https://github.com/svenfuchs/globalize-rails.org","watchers":3,"description":"","fork":false,"has_wiki":true,"open_issues":0,"homepage":"globalize-rails.org","size":1988,"private":false,"name":"globalize-rails.org","forks":1,"owner":"svenfuchs","has_issues":true,"created_at":"2010/08/30 05:40:45 -0700","pushed_at":"2010/10/04 02:34:11 -0700"},{"has_downloads":true,"url":"https://github.com/svenfuchs/adva-cms.org","watchers":3,"description":"","fork":false,"has_wiki":true,"open_issues":0,"homepage":"adva-cms.org","size":6580,"private":false,"name":"adva-cms.org","forks":1,"owner":"svenfuchs","has_issues":true,"language":"Ruby","created_at":"2010/08/31 02:33:27 -0700","pushed_at":"2011/02/28 11:52:02 -0800"},{"has_downloads":true,"url":"https://github.com/svenfuchs/inherited_resources_helpers","watchers":5,"fork":false,"has_wiki":true,"open_issues":0,"size":156,"private":false,"name":"inherited_resources_helpers","forks":2,"owner":"svenfuchs","has_issues":true,"language":"Ruby","created_at":"2010/09/11 04:48:44 -0700","pushed_at":"2011/06/28 04:26:32 -0700"},{"has_downloads":true,"url":"https://github.com/svenfuchs/vim-deliminator","watchers":1,"description":"Balancing brackets and quotes","fork":false,"has_wiki":true,"open_issues":0,"homepage":"","size":584,"private":false,"name":"vim-deliminator","forks":1,"owner":"svenfuchs","has_issues":true,"created_at":"2010/10/04 00:35:12 -0700","pushed_at":"2010/10/06 05:36:52 -0700"},{"has_downloads":true,"url":"https://github.com/svenfuchs/vim-layout","watchers":4,"description":"","fork":false,"has_wiki":true,"open_issues":0,"homepage":"","size":368,"private":false,"name":"vim-layout","forks":3,"owner":"svenfuchs","has_issues":true,"language":"Ruby","created_at":"2010/10/17 10:57:26 -0700","pushed_at":"2010/10/17 10:57:46 -0700"},{"has_downloads":true,"url":"https://github.com/svenfuchs/i18n-active_record","watchers":36,"description":"I18n ActiveRecord backend","fork":false,"has_wiki":true,"open_issues":6,"homepage":"","size":256,"private":false,"name":"i18n-active_record","forks":14,"owner":"svenfuchs","has_issues":true,"language":"Ruby","created_at":"2010/11/05 05:25:03 -0700","pushed_at":"2011/07/06 20:18:33 -0700"},{"has_downloads":true,"url":"https://github.com/svenfuchs/i18n-missing_translations","watchers":3,"description":"Find missing translations in your code more easily.","fork":false,"has_wiki":true,"open_issues":0,"homepage":"","size":452,"private":false,"name":"i18n-missing_translations","forks":2,"owner":"svenfuchs","has_issues":true,"language":"Ruby","created_at":"2010/11/06 03:31:16 -0700","pushed_at":"2010/11/06 08:36:02 -0700"},{"has_downloads":true,"url":"https://github.com/svenfuchs/vim-todo","watchers":8,"description":"Provides a simple todo list similar to Textmate’s todo.bundle","fork":false,"has_wiki":true,"open_issues":1,"homepage":"","size":240,"private":false,"name":"vim-todo","forks":2,"owner":"svenfuchs","has_issues":true,"language":"Ruby","created_at":"2010/11/06 19:23:35 -0700","pushed_at":"2010/11/07 06:43:19 -0800"},{"has_downloads":true,"url":"https://github.com/svenfuchs/activesupport-slices","watchers":14,"description":"Lazy loaded vertical code slices based on ActiveSupport Dependencies","fork":false,"has_wiki":true,"open_issues":0,"homepage":"","size":116,"private":false,"name":"activesupport-slices","forks":2,"owner":"svenfuchs","has_issues":true,"language":"Ruby","created_at":"2010/11/14 04:06:24 -0800","pushed_at":"2011/06/16 05:11:00 -0700"},{"has_downloads":true,"url":"https://github.com/svenfuchs/ruby-i18n.tmbundle","watchers":4,"description":"","fork":false,"has_wiki":true,"open_issues":0,"homepage":"","size":264,"private":false,"name":"ruby-i18n.tmbundle","forks":1,"owner":"svenfuchs","has_issues":true,"language":"Ruby","created_at":"2010/12/26 12:18:29 -0800","pushed_at":"2010/12/26 13:07:21 -0800"},{"has_downloads":true,"url":"https://github.com/svenfuchs/rails-i18n-chart","watchers":1,"description":"","fork":false,"has_wiki":true,"open_issues":0,"homepage":"","size":312,"private":false,"name":"rails-i18n-chart","forks":1,"owner":"svenfuchs","has_issues":true,"created_at":"2010/12/26 13:14:25 -0800","pushed_at":"2010/12/26 13:15:29 -0800"},{"has_downloads":true,"url":"https://github.com/svenfuchs/database_recorder","watchers":1,"description":"","fork":false,"has_wiki":true,"open_issues":0,"homepage":"","size":332,"private":false,"name":"database_recorder","forks":1,"owner":"svenfuchs","has_issues":true,"language":"Ruby","created_at":"2011/02/09 08:32:22 -0800","pushed_at":"2011/02/09 09:39:40 -0800"},{"has_downloads":true,"url":"https://github.com/svenfuchs/travis","watchers":1,"description":"","fork":false,"has_wiki":true,"open_issues":0,"homepage":"","size":108,"private":false,"name":"travis","forks":1,"owner":"svenfuchs","has_issues":true,"created_at":"2011/02/27 13:56:39 -0800","pushed_at":"2011/02/28 13:40:09 -0800"},{"has_downloads":true,"url":"https://github.com/svenfuchs/sproutcore","watchers":1,"description":"JavaScript Application Framework - JS library only","fork":true,"has_wiki":true,"open_issues":0,"homepage":"sproutcore.com","size":6528,"private":false,"name":"sproutcore","forks":0,"owner":"svenfuchs","has_issues":false,"language":"JavaScript","integrate_branch":"1-5-stable","created_at":"2011/04/27 10:34:00 -0700","pushed_at":"2011/04/27 10:36:21 -0700"},{"has_downloads":true,"url":"https://github.com/svenfuchs/resque-heartbeat","watchers":4,"fork":false,"has_wiki":true,"open_issues":0,"size":316,"private":false,"name":"resque-heartbeat","forks":1,"owner":"svenfuchs","has_issues":true,"language":"Ruby","created_at":"2011/06/06 02:11:05 -0700","pushed_at":"2011/06/17 08:43:33 -0700"},{"has_downloads":true,"url":"https://github.com/svenfuchs/em-stdout","watchers":2,"fork":false,"has_wiki":true,"open_issues":0,"size":140,"private":false,"name":"em-stdout","forks":1,"owner":"svenfuchs","has_issues":true,"language":"Ruby","created_at":"2011/06/07 09:25:17 -0700","pushed_at":"2011/06/07 09:28:56 -0700"},{"has_downloads":true,"url":"https://github.com/svenfuchs/net-ssh-shell","watchers":1,"description":"A net-ssh extension library that provides an API for programmatically interacting with a login shell","fork":true,"has_wiki":true,"open_issues":0,"homepage":"http://rubyforge.org/projects/net-ssh","size":828,"private":false,"name":"net-ssh-shell","forks":0,"owner":"svenfuchs","has_issues":false,"language":"Ruby","created_at":"2011/06/10 03:48:02 -0700","pushed_at":"2011/06/10 03:52:55 -0700"},{"has_downloads":true,"url":"https://github.com/svenfuchs/vagrant","watchers":1,"description":"Vagrant is a tool for building and distributing virtualized development environments.","fork":true,"has_wiki":true,"open_issues":0,"homepage":"http://vagrantup.com","size":128,"private":false,"name":"vagrant","forks":0,"owner":"svenfuchs","has_issues":false,"language":"Ruby","created_at":"2011/07/09 17:02:24 -0700","pushed_at":"2011/07/09 17:03:34 -0700"},{"has_downloads":true,"url":"https://github.com/svenfuchs/hashr","watchers":25,"description":"Simple Hash extension to make working with nested hashes (e.g. for configuration) easier and less error-prone.","fork":false,"has_wiki":true,"open_issues":0,"homepage":"http://github.com/svenfuchs/hashr","size":416,"private":false,"name":"hashr","forks":1,"owner":"svenfuchs","has_issues":true,"language":"Ruby","created_at":"2011/07/23 09:29:11 -0700","pushed_at":"2011/08/07 06:28:36 -0700"},{"has_downloads":true,"url":"https://github.com/svenfuchs/cmusv","watchers":1,"description":" Carnegie Mellon University - Silicon Valley Campus - Learn By Doing Curriculum Tool","fork":true,"has_wiki":true,"open_issues":0,"homepage":"","size":116,"private":false,"master_branch":"rails-3","name":"cmusv","forks":0,"owner":"svenfuchs","has_issues":false,"language":"Ruby","created_at":"2011/07/28 15:00:33 -0700","pushed_at":"2011/07/28 15:01:12 -0700"},{"has_downloads":true,"url":"https://github.com/svenfuchs/resque-tagged_queues","watchers":2,"description":"","fork":false,"has_wiki":true,"open_issues":0,"homepage":"","size":96,"private":false,"name":"resque-tagged_queues","forks":1,"owner":"svenfuchs","has_issues":true,"language":"Ruby","created_at":"2011/07/30 18:08:40 -0700","pushed_at":"2011/07/30 18:09:03 -0700"},{"has_downloads":true,"url":"https://github.com/svenfuchs/simple_states","watchers":5,"fork":false,"has_wiki":true,"open_issues":0,"size":276,"private":false,"name":"simple_states","forks":1,"owner":"svenfuchs","has_issues":true,"language":"Ruby","created_at":"2011/07/31 13:17:20 -0700","pushed_at":"2011/08/07 11:22:34 -0700"}]}
